swagger_ui_bundle/__init__.py
swagger_ui_bundle/vendor/swagger-ui-2.2.10/index.html
swagger_ui_bundle/vendor/swagger-ui-2.2.10/index.j2
swagger_ui_bundle/vendor/swagger-ui-2.2.10/o2c.html
swagger_ui_bundle/vendor/swagger-ui-2.2.10/swagger-ui.js
swagger_ui_bundle/vendor/swagger-ui-2.2.10/swagger-ui.min.js
swagger_ui_bundle/vendor/swagger-ui-2.2.10/css/print.css
swagger_ui_bundle/vendor/swagger-ui-2.2.10/css/reset.css
swagger_ui_bundle/vendor/swagger-ui-2.2.10/css/screen.css
swagger_ui_bundle/vendor/swagger-ui-2.2.10/css/style.css
swagger_ui_bundle/vendor/swagger-ui-2.2.10/css/typography.css
swagger_ui_bundle/vendor/swagger-ui-2.2.10/fonts/DroidSans-Bold.ttf
swagger_ui_bundle/vendor/swagger-ui-2.2.10/fonts/DroidSans.ttf
swagger_ui_bundle/vendor/swagger-ui-2.2.10/images/collapse.gif
swagger_ui_bundle/vendor/swagger-ui-2.2.10/images/expand.gif
swagger_ui_bundle/vendor/swagger-ui-2.2.10/images/explorer_icons.png
swagger_ui_bundle/vendor/swagger-ui-2.2.10/images/favicon-16x16.png
swagger_ui_bundle/vendor/swagger-ui-2.2.10/images/favicon-32x32.png
swagger_ui_bundle/vendor/swagger-ui-2.2.10/images/favicon.ico
swagger_ui_bundle/vendor/swagger-ui-2.2.10/images/logo_small.png
swagger_ui_bundle/vendor/swagger-ui-2.2.10/images/pet_store_api.png
swagger_ui_bundle/vendor/swagger-ui-2.2.10/images/throbber.gif
swagger_ui_bundle/vendor/swagger-ui-2.2.10/images/wordnik_api.png
swagger_ui_bundle/vendor/swagger-ui-2.2.10/lang/ca.js
swagger_ui_bundle/vendor/swagger-ui-2.2.10/lang/el.js
swagger_ui_bundle/vendor/swagger-ui-2.2.10/lang/en.js
swagger_ui_bundle/vendor/swagger-ui-2.2.10/lang/es.js
swagger_ui_bundle/vendor/swagger-ui-2.2.10/lang/fr.js
swagger_ui_bundle/vendor/swagger-ui-2.2.10/lang/geo.js
swagger_ui_bundle/vendor/swagger-ui-2.2.10/lang/it.js
swagger_ui_bundle/vendor/swagger-ui-2.2.10/lang/ja.js
swagger_ui_bundle/vendor/swagger-ui-2.2.10/lang/ko-kr.js
swagger_ui_bundle/vendor/swagger-ui-2.2.10/lang/pl.js
swagger_ui_bundle/vendor/swagger-ui-2.2.10/lang/pt.js
swagger_ui_bundle-0.0.9.dist-info/LICENSE
swagger_ui_bundle-0.0.9.dist-info/METADATA
swagger_ui_bundle-0.0.9.dist-info/WHEEL
swagger_ui_bundle-0.0.9.dist-info/top_level.txt
swagger_ui_bundle-0.0.9.dist-info/RECORD
