Metadata-Version: 1.1
Name: swagger-ui-bundle
Version: 0.0.9
Summary: swagger_ui_bundle - swagger-ui files in a pip package
Home-page: https://github.com/dtkav/swagger_ui_bundle
Author: Daniel Grossmann-Kavanagh
Author-email: UNKNOWN
License: Apache License Version 2.0
Keywords: swagger-ui
Platform: UNKNOWN
Classifier: Programming Language :: Python
Classifier: Programming Language :: Python :: 2.7
Classifier: Programming Language :: Python :: 3.4
Classifier: Programming Language :: Python :: 3.5
Classifier: Programming Language :: Python :: 3.6
Classifier: Development Status :: 5 - Production/Stable
Classifier: Intended Audience :: Developers
Classifier: Operating System :: OS Independent
